CCAgT_utils/__init__.py
CCAgT_utils/__main__.py
CCAgT_utils/categories.py
CCAgT_utils/checkers.py
CCAgT_utils/constants.py
CCAgT_utils/describe.py
CCAgT_utils/errors.py
CCAgT_utils/main.py
CCAgT_utils/prepare.py
CCAgT_utils/slice.py
CCAgT_utils/split.py
CCAgT_utils/utils.py
CCAgT_utils/converters/CCAgT.py
CCAgT_utils/converters/COCO.py
CCAgT_utils/converters/LabelBox.py
CCAgT_utils/converters/__init__.py
CCAgT_utils/converters/__main__.py
CCAgT_utils/converters/main.py
CCAgT_utils/converters/masks.py
CCAgT_utils/converters/utils.py
CCAgT_utils/types/__init__.py
CCAgT_utils/types/alias.py
CCAgT_utils/types/annotation.py
CCAgT_utils/types/checkers.py
CCAgT_utils/types/colors.py
CCAgT_utils/types/mask.py
CCAgT_utils/visualization/__init__.py
CCAgT_utils/visualization/__main__.py
CCAgT_utils/visualization/_show.py
CCAgT_utils/visualization/main.py
CCAgT_utils/visualization/plot.py
CCAgT_utils-0.1.1.dist-info/LICENSE
CCAgT_utils-0.1.1.dist-info/METADATA
CCAgT_utils-0.1.1.dist-info/WHEEL
CCAgT_utils-0.1.1.dist-info/entry_points.txt
CCAgT_utils-0.1.1.dist-info/top_level.txt
CCAgT_utils-0.1.1.dist-info/RECORD
