Metadata-Version: 2.1
Name: CCAgT-utils
Version: 0.1.1
Summary: A framework of utilities to help at the use of the CCAgT dataset
Home-page: https://github.com/johnnv1/CCAgT_dataset_utils
Author: João Gustavo Atkinson Amorim
Author-email: joaogustavoamorim@gmail.com
License: Apache-2.0
Classifier: License :: OSI Approved :: Apache Software License
Classifier: Programming Language :: Python :: 3
Classifier: Programming Language :: Python :: 3 :: Only
Classifier: Programming Language :: Python :: Implementation :: CPython
Classifier: Programming Language :: Python :: Implementation :: PyPy
Requires-Python: >=3.8
License-File: LICENSE
Requires-Dist: matplotlib (>=3.5.1)
Requires-Dist: networkx (>=2.6.3)
Requires-Dist: numpy (>=1.21.5)
Requires-Dist: pandas (>=1.1.5)
Requires-Dist: pillow (>=9.0.1)
Requires-Dist: pyarrow (>=7.0.0)
Requires-Dist: shapely (>=1.8.0)
